src/3-stage-pipeline/opcode.vh
//  OPCODE and parameter definitions

`define OPCODE      6:0
`define FUNC3       14:12
`define SUBTYPE     30
`define RD          11:7
`define RS1         19:15
`define RS2         24:20


localparam  [31: 0] NOP        = 32'h0000_0013;     // addi x0, x0, 0

// OPCODE, INST[6:0]
localparam  [ 6: 0] LUI     = 7'b0110111,        // U-type
                    JAL     = 7'b1101111,        // J-type
                    JALR    = 7'b1100111,        // I-type
                    BRANCH  = 7'b1100011,        // B-type
                    LOAD    = 7'b0000011,        // I-type
                    STORE   = 7'b0100011,        // S-type
                    ARITHI  = 7'b0010011,        // I-type
                    ARITHR  = 7'b0110011;        // R-type



// FUNC3, INST[14:12], INST[6:0] = 7'b1100011
localparam  [ 2: 0] BEQ     = 3'b000,
                    BNE     = 3'b001,
                    BLT     = 3'b100,
                    BGE     = 3'b101,
                    BLTU    = 3'b110,
                    BGEU    = 3'b111;

// FUNC3, INST[14:12], INST[6:0] = 7'b0000011
localparam  [ 2: 0] LB      = 3'b000,
                    LH      = 3'b001,
                    LW      = 3'b010,
                    LBU     = 3'b100,
                    LHU     = 3'b101;

// FUNC3, INST[14:12], INST[6:0] = 7'b0100011
localparam  [ 2: 0] SB      = 3'b000,
                    SH      = 3'b001,
                    SW      = 3'b010;
                    
// FUNC3, INST[14:12], INST[6:0] = 7'b0110011, 7'b0010011
localparam  [ 2: 0] ADD     = 3'b000,    // inst[30] == 0: ADD, inst[31] == 1: SUB
                    SLL     = 3'b001,
                    SLT     = 3'b010,
                    SLTU    = 3'b011,
                    XOR     = 3'b100,
                    SR      = 3'b101,    // inst[30] == 0: SRL, inst[31] == 1: SRA
                    OR      = 3'b110,
                    AND     = 3'b111;

// =================================================================
// DSP / M-EXTENSION IDENTIFIERS (FUNC7)
// These share the ARITHR opcode (7'b0110011)
// =================================================================
localparam [6:0] M_EXT   = 7'b0000001; // Standard RV32M Extension
localparam [6:0] MAC_EXT = 7'b0000010; // Custom DSP Extension

// =================================================================
// RV32M FUNC3 DEFINITIONS (When FUNC7 == M_EXT)
// =================================================================
localparam [2:0] MUL    = 3'b000, // Lower 32 bits of Rs1 * Rs2
                 MULH   = 3'b001, // Upper 32 bits (Signed x Signed)
                 MULHSU = 3'b010, // Upper 32 bits (Signed x Unsigned)
                 MULHU  = 3'b011, // Upper 32 bits (Unsigned x Unsigned)
                 DIV    = 3'b100, // Rs1 / Rs2 (Signed)
                 DIVU   = 3'b101, // Rs1 / Rs2 (Unsigned)
                 REM    = 3'b110, // Remainder (Signed)
                 REMU   = 3'b111; // Remainder (Unsigned)

// =================================================================
// CUSTOM MAC FUNC3 DEFINITIONS (When FUNC7 == MAC_EXT)
// =================================================================
localparam [2:0] MAC    = 3'b000, // Accumulator = Accumulator + (Rs1 * Rs2)
                 MVACC  = 3'b001; // Rd = Accumulator

src/math_coproc.v
`timescale 1ns/1ps

module math_coproc (
    input  wire        clk,
    input  wire        reset,
    
    // Data Inputs from Execute Stage
    input  wire [31:0] rs1_data,
    input  wire [31:0] rs2_data,
    
    // Control Inputs from Decode Stage
    input  wire [2:0]  mul_op,      // FUNC3 from the instruction
    input  wire        is_m_ext,    // High if instruction is standard MUL
    input  wire        is_mac,      // High if instruction is MAC
    input  wire        is_mvacc,    // High if instruction is MVACC
    input  wire        pipeline_stall, // Prevents accumulator from updating during a stall
    
    // Outputs back to Execute Stage
    output reg  [31:0] math_result,
    output wire        math_stall    // PLACEHOLDER: Will be used when we build the Divider!
);

`include "opcode.vh"
    // Default stall to 0 for now. The pipeline will only freeze when we build the DIV state machine.
    assign math_stall = 1'b0; 

    // =================================================================
    // 1. THE MULTIPLIER (Combinational)
    // =================================================================
    
    // We must carefully extend the 32-bit inputs to 33 bits to handle signed vs unsigned math.
    // If the operation is unsigned (MULHU), we pad with a 0. Otherwise, we sign-extend.
    wire signed [32:0] op1_ext = (mul_op == MULHU) ? {1'b0, rs1_data} : {rs1_data[31], rs1_data};
    wire signed [32:0] op2_ext = (mul_op == MULHU || mul_op == MULHSU) ? {1'b0, rs2_data} : {rs2_data[31], rs2_data};

    // Calculate the full 64-bit product instantly
    (* use_dsp = "yes" *)wire signed [65:0] full_product = op1_ext * op2_ext;

    // =================================================================
    // 2. THE HIDDEN ACCUMULATOR (Synchronous)
    // =================================================================
   // Tell Vivado: "Do not build this out of standard logic gates! Use a DSP slice!"
(* use_dsp = "yes" *) reg [31:0] mac_accumulator;

    always @(posedge clk or negedge reset) begin
        if (!reset) begin
            mac_accumulator <= 32'h0;
        end
        // Only do the math if it's a MAC instruction AND the CPU isn't frozen
        else if (is_mac && !pipeline_stall) begin
            // Accumulator = Accumulator + (Lower 32 bits of Rs1 * Rs2)
            mac_accumulator <= mac_accumulator + full_product[31:0];
        end
    end

    // =================================================================
    // 3. OUTPUT ROUTING (Combinational)
    // =================================================================
    
    always @(*) begin
        if (is_mvacc) begin
            // MVACC Instruction: Dump the hidden accumulator out to the CPU
            math_result = mac_accumulator;
        end 
        else if (is_m_ext) begin
            // Standard RV32M Instructions: Route the correct slice of the 64-bit product
            case (mul_op)
                MUL:    math_result = full_product[31:0];  // Lower 32 bits
                MULH:   math_result = full_product[63:32]; // Upper 32 (Signed x Signed)
                MULHSU: math_result = full_product[63:32]; // Upper 32 (Signed x Unsigned)
                MULHU:  math_result = full_product[63:32]; // Upper 32 (Unsigned x Unsigned)
                default: math_result = 32'h0;
            endcase
        end 
        else begin
            math_result = 32'h0;
        end
    end

endmodule

tb/tb_math_coproc.v
`timescale 1ns / 1ps

module tb_math_coproc;

    // ---------------------------------------------------------
    // 1. Inputs (Registers) and Outputs (Wires)
    // ---------------------------------------------------------
    reg         clk;
    reg         reset;
    reg  [31:0] rs1_data;
    reg  [31:0] rs2_data;
    reg  [2:0]  mul_op;
    reg         is_m_ext;
    reg         is_mac;
    reg         is_mvacc;
    reg         pipeline_stall;
    
    wire [31:0] math_result;
    wire        math_stall;

`include "opcode.vh"
    // ---------------------------------------------------------
    // 2. Instantiate the Unit Under Test (UUT)
    // ---------------------------------------------------------
    math_coproc UUT (
        .clk(clk),
        .reset(reset),
        .rs1_data(rs1_data),
        .rs2_data(rs2_data),
        .mul_op(mul_op),
        .is_m_ext(is_m_ext),
        .is_mac(is_mac),
        .is_mvacc(is_mvacc),
        .pipeline_stall(pipeline_stall),
        .math_result(math_result),
        .math_stall(math_stall)
    );

    // ---------------------------------------------------------
    // 3. Clock Generation (10ns period)
    // ---------------------------------------------------------
    initial begin
        clk = 0;
        forever #5 clk = ~clk;
    end

    // ---------------------------------------------------------
    // 4. The Test Sequence
    // ---------------------------------------------------------
    initial begin
        // Setup Waveform Dump
        $dumpfile("math_coproc.vcd");
        $dumpvars(0, tb_math_coproc);

        // Initialize Inputs
        reset = 0;
        rs1_data = 0; rs2_data = 0; mul_op = 0;
        is_m_ext = 0; is_mac = 0; is_mvacc = 0; pipeline_stall = 0;

        // Apply Reset
        #10;
        reset = 1;
        #10;

        $display("==================================================");
        $display("   STARTING MATH COPROCESSOR UNIT TEST   ");
        $display("==================================================");

        // -----------------------------------------------------
        // TEST 1: Standard Multiplication (5 * 6 = 30)
        // -----------------------------------------------------
        $display("-> Executing: MUL (5 * 6)");
        rs1_data = 32'd5;
        rs2_data = 32'd6;
        mul_op   = MUL;
        is_m_ext = 1; is_mac = 0; is_mvacc = 0;
        #10; 
        $display("   Result: %0d (Expected: 30)", $signed(math_result));

        // -----------------------------------------------------
        // TEST 2: First MAC Instruction (Acc = 0 + (4 * 5))
        // -----------------------------------------------------
        $display("\n-> Executing: MAC (4 * 5)");
        rs1_data = 32'd4;
        rs2_data = 32'd5;
        mul_op   = MAC;
        is_m_ext = 0; is_mac = 1; is_mvacc = 0;
        #10; // Wait a cycle for the accumulator to update
        
        // -----------------------------------------------------
        // TEST 3: Second MAC Instruction (Acc = 20 + (2 * 3))
        // -----------------------------------------------------
        $display("-> Executing: MAC (2 * 3)");
        rs1_data = 32'd2;
        rs2_data = 32'd3;
        mul_op   = MAC;
        is_m_ext = 0; is_mac = 1; is_mvacc = 0;
        #10; // Wait a cycle for the accumulator to update
        
        // -----------------------------------------------------
        // TEST 4: MVACC (Retrieve the Accumulator)
        // -----------------------------------------------------
        $display("\n-> Executing: MVACC (Retrieving Accumulator)");
        rs1_data = 32'd0; // Doesn't matter
        rs2_data = 32'd0; // Doesn't matter
        mul_op   = MVACC;
        is_m_ext = 0; is_mac = 0; is_mvacc = 1;
        #10;
        $display("   Result: %0d (Expected: 26)", $signed(math_result));

        // -----------------------------------------------------
        // TEST 5: Pipeline Stall Block Test
        // -----------------------------------------------------
        $display("\n-> Executing: MAC (10 * 10) with PIPELINE STALL");
        rs1_data = 32'd10;
        rs2_data = 32'd10;
        mul_op   = MAC;
        is_m_ext = 0; is_mac = 1; is_mvacc = 0; 
        pipeline_stall = 1; // Simulate a CPU freeze!
        #10;
        
        // Check if it ignored the math because of the stall
        is_m_ext = 0; is_mac = 0; is_mvacc = 1; pipeline_stall = 0;
        #10;
        $display("   Result: %0d (Expected: 26, because stall blocked the 100)", $signed(math_result));

        $display("==================================================");
        // -----------------------------------------------------
        // TEST 6: Negative Multiplication (MUL)
        // -----------------------------------------------------
        $display("\n-> Executing: MUL (-5 * 6)");
        rs1_data = -32'd5;
        rs2_data = 32'd6;
        mul_op   = MUL;
        is_m_ext = 1; is_mac = 0; is_mvacc = 0; pipeline_stall = 0;
        #10;
        $display("   Result: %0d (Expected: -30)", $signed(math_result));

        // -----------------------------------------------------
        // TEST 7: Negative MAC Accumulation
        // -----------------------------------------------------
        // The accumulator is currently sitting at 26 (from Test 4). 
        // Let's add -20 to it.
        $display("\n-> Executing: MAC (-4 * 5) [Acc is currently 26]");
        rs1_data = -32'd4;
        rs2_data = 32'd5;
        mul_op   = MAC;
        is_m_ext = 0; is_mac = 1; is_mvacc = 0;
        #10; // Wait a cycle for accumulator to latch
        
        $display("-> Executing: MVACC (Retrieving Accumulator)");
        mul_op   = MVACC;
        is_m_ext = 0; is_mac = 0; is_mvacc = 1;
        #10;
        $display("   Result: %0d (Expected: 6, because 26 - 20 = 6)", $signed(math_result));

        // -----------------------------------------------------
        // TEST 8: Signed vs Unsigned 64-bit Boundaries (MULH vs MULHU)
        // -----------------------------------------------------
        // We will multiply 0xFFFFFFFF by 2.
        // In Signed math: this is (-1 * 2) = -2.
        // In Unsigned math: this is (4,294,967,295 * 2) = 8,589,934,590.
        $display("\n-> Executing: High Multiplication Bound Test");
        rs1_data = 32'hFFFFFFFF; 
        rs2_data = 32'h00000002; 
        
        // Test MULH (Signed x Signed)
        mul_op   = MULH;
        is_m_ext = 1; is_mac = 0; is_mvacc = 0;
        #10;
        $display("   MULH  Result: %h (Expected: ffffffff, the upper 32 bits of -2)", math_result);
        
        // Test MULHU (Unsigned x Unsigned)
        mul_op   = MULHU;
        #10;
        $display("   MULHU Result: %h (Expected: 00000001, the upper 32 bits of 8,589,934,590)", math_result);

        // -----------------------------------------------------
        // TEST 9: Hardware Reset
        // -----------------------------------------------------
        // The accumulator is currently at 6. If we hit the reset button, it should wipe to 0.
        $display("\n-> Executing: Hardware Reset Test");
        reset = 0; // Trigger Active-Low Reset
        #10;
        reset = 1; // Release Reset
        
        // Read the accumulator again
        mul_op   = MVACC;
        is_m_ext = 0; is_mac = 0; is_mvacc = 1;
        #10;
        $display("   Result after reset: %0d (Expected: 0)", $signed(math_result));
        $finish;
    end

endmodule

tb/math_coproc.vcd
$date
   Thu Apr  2 21:30:16 2026
$end

$version
  2025.2
  $dumpfile ("math_coproc.vcd") 
$end

$timescale
  1ps
$end

$scope module tb_math_coproc $end
$var reg 1 ! clk $end
$var reg 1 " reset $end
$var reg 32 # rs1_data [31:0] $end
$var reg 32 $ rs2_data [31:0] $end
$var reg 3 % mul_op [2:0] $end
$var reg 1 & is_m_ext $end
$var reg 1 ' is_mac $end
$var reg 1 ( is_mvacc $end
$var reg 1 ) pipeline_stall $end
$var wire 32 * math_result [31:0] $end
$var wire 1 + math_stall $end
$scope module UUT $end
$var wire 1 , clk $end
$var wire 1 - reset $end
$var wire 32 . rs1_data [31:0] $end
$var wire 32 / rs2_data [31:0] $end
$var wire 3 0 mul_op [2:0] $end
$var wire 1 1 is_m_ext $end
$var wire 1 2 is_mac $end
$var wire 1 3 is_mvacc $end
$var wire 1 4 pipeline_stall $end
$var reg 32 5 math_result [31:0] $end
$var wire 1 + math_stall $end
$var wire 33 6 op1_ext [32:0] $end
$var wire 33 7 op2_ext [32:0] $end
$var wire 66 8 full_product [65:0] $end
$var reg 32 9 mac_accumulator [31:0] $end
$upscope $end
$upscope $end
$enddefinitions $end

#0
$dumpvars
0!
0"
b0 #
b0 $
b0 %
0&
0'
0(
0)
b0 *
0+
0,
0-
b0 .
b0 /
b0 0
01
02
03
04
b0 5
b0 6
b0 7
b0 8
b0 9
$end

#5000
1!
1,

#10000
0!
1"
0,
1-

#15000
1!
1,

#20000
0!
b101 #
b110 $
1&
b11110 *
0,
b101 .
b110 /
11
b11110 5
b101 6
b110 7
b11110 8

#25000
1!
1,

#30000
0!
b100 #
b101 $
0&
1'
b0 *
0,
b100 .
b101 /
01
12
b0 5
b100 6
b101 7
b10100 8

#35000
1!
1,
b10100 9

#40000
0!
b10 #
b11 $
0,
b10 .
b11 /
b10 6
b11 7
b110 8

#45000
1!
1,
b11010 9

#50000
0!
b0 #
b0 $
b1 %
0'
1(
b11010 *
0,
b0 .
b0 /
b1 0
02
13
b11010 5
b0 6
b0 7
b0 8

#55000
1!
1,

#60000
0!
b1010 #
b1010 $
b0 %
1'
0(
1)
b0 *
0,
b1010 .
b1010 /
b0 0
12
03
14
b0 5
b1010 6
b1010 7
b1100100 8

#65000
1!
1,

#70000
0!
0'
1(
0)
b11010 *
0,
02
13
04
b11010 5

#75000
1!
1,

#80000
0!
b11111111111111111111111111111011 #
b110 $
1&
0(
b11111111111111111111111111100010 *
0,
b11111111111111111111111111111011 .
b110 /
11
03
b11111111111111111111111111100010 5
b111111111111111111111111111111011 6
b110 7
b111111111111111111111111111111111111111111111111111111111111100010 8

#85000
1!
1,

#90000
0!
b11111111111111111111111111111100 #
b101 $
0&
1'
b0 *
0,
b11111111111111111111111111111100 .
b101 /
01
12
b0 5
b111111111111111111111111111111100 6
b101 7
b111111111111111111111111111111111111111111111111111111111111101100 8

#95000
1!
1,
b110 9

#100000
0!
b1 %
0'
1(
b110 *
0,
b1 0
02
13
b110 5

#105000
1!
1,

#110000
0!
b11111111111111111111111111111111 #
b10 $
1&
0(
b11111111111111111111111111111111 *
0,
b11111111111111111111111111111111 .
b10 /
11
03
b11111111111111111111111111111111 5
b111111111111111111111111111111111 6
b10 7
b111111111111111111111111111111111111111111111111111111111111111110 8

#115000
1!
1,

#120000
0!
b11 %
b1 *
0,
b11 0
b1 5
b11111111111111111111111111111111 6
b111111111111111111111111111111110 8

#125000
1!
1,

#130000
0!
0"
0,
0-
b0 9

#135000
1!
1,

#140000
0!
1"
b1 %
0&
1(
b0 *
0,
1-
b1 0
01
13
b0 5
b111111111111111111111111111111111 6
b111111111111111111111111111111111111111111111111111111111111111110 8

